binary_classification_ratios/__init__.py
binary_classification_ratios/ratios.py
binary_classification_ratios/summary.py
binary_classification_ratios/cli/__init__.py
binary_classification_ratios/cli/cmd_line.py
binary_classification_ratios/cli/main.py
binary_classification_ratios-0.3.0.dist-info/METADATA
binary_classification_ratios-0.3.0.dist-info/WHEEL
binary_classification_ratios-0.3.0.dist-info/entry_points.txt
binary_classification_ratios-0.3.0.dist-info/RECORD
