Metadata-Version: 2.4
Name: binary-classification-ratios
Version: 0.3.0
Summary: Binary classification ratios gathered in one package.
Project-URL: Repository, https://github.com/kovalp/binary_classification_ratios
Project-URL: Issues, https://github.com/kovalp/binary_classification_ratios/issues
Author-email: Peter Koval <koval.peter@gmail.com>
License: MIT
Classifier: Operating System :: OS Independent
Classifier: Programming Language :: Python :: 3
Classifier: Topic :: Scientific/Engineering
Requires-Python: <4.0,>=3.8
